sa_repository/__init__.py
sa_repository/base.py
sa_repository-1.1.1.dist-info/LICENSE
sa_repository-1.1.1.dist-info/METADATA
sa_repository-1.1.1.dist-info/WHEEL
sa_repository-1.1.1.dist-info/RECORD
