Metadata-Version: 2.1
Name: sa-repository
Version: 1.1.1
Summary: Repository pattern for SQLAlchemy models
Home-page: https://github.com/Gasper3/sa-repository
License: MIT
Keywords: sqlalchemy,repository-pattern,orm,repository
Author: Gasper3
Author-email: trzecik65@gmail.com
Requires-Python: >=3.10,<4.0
Classifier: Development Status :: 5 - Production/Stable
Classifier: Intended Audience :: Developers
Classifier: License :: OSI Approved :: MIT License
Classifier: Programming Language :: Python :: 3
Classifier: Programming Language :: Python :: 3.10
Classifier: Programming Language :: Python :: 3.11
Classifier: Programming Language :: Python :: 3.12
Classifier: Topic :: Database
Requires-Dist: more-itertools (>=9.1.0,<10.0.0)
Requires-Dist: sqlalchemy (>=2.0.2,<3.0.0)
Project-URL: Repository, https://github.com/Gasper3/sa-repository
